<?xml version="1.0" encoding="UTF-8"?><record_update table="ais_datasource_field_attribute">
    <ais_datasource_field_attribute action="INSERT_OR_UPDATE">
        <attribute display_value="map_to">f734a634c7320010d1cfd9795cc26094</attribute>
        <datasource display_value="Approval Table">761f2ef783d856900bafad20ceaad325</datasource>
        <field>document_id</field>
        <source>sysapproval_approver</source>
        <sys_class_name>ais_datasource_field_attribute</sys_class_name>
        <sys_created_by>admin</sys_created_by>
        <sys_created_on>2024-09-04 15:16:48</sys_created_on>
        <sys_id>3e1f2ef783d856900bafad20ceaad371</sys_id>
        <sys_mod_count>0</sys_mod_count>
        <sys_name>sysapproval_approver.document_id</sys_name>
        <sys_package display_value="Claims Management System - Raj" source="x_1523132_claims_m">55a74ce683d096100bafad20ceaad3c3</sys_package>
        <sys_policy/>
        <sys_scope display_value="Claims Management System - Raj">55a74ce683d096100bafad20ceaad3c3</sys_scope>
        <sys_update_name>ais_datasource_field_attribute_3e1f2ef783d856900bafad20ceaad371</sys_update_name>
        <sys_updated_by>admin</sys_updated_by>
        <sys_updated_on>2024-09-04 15:16:48</sys_updated_on>
        <value>title</value>
    </ais_datasource_field_attribute>
</record_update>
